{
  "fonte": "Open-Meteo",
  "coletado_em": "2026-04-13T12:11:55.879957",
  "horizonte_dias": 16,
  "dias": [
    {
      "data": "2026-04-13",
      "chuva_mm": 15.2,
      "prob_chuva_pct": 93,
      "temp_max_c": 27.9,
      "temp_min_c": 24.5,
      "umidade_max_pct": 97,
      "umidade_min_pct": 86,
      "vento_max_kmh": 5.2,
      "rajada_max_kmh": 18.4,
      "radiacao_mj_m2": 9.03,
      "evapotranspiracao_mm": 1.88
    },
    {
      "data": "2026-04-14",
      "chuva_mm": 7.2,
      "prob_chuva_pct": 40,
      "temp_max_c": 31.0,
      "temp_min_c": 24.1,
      "umidade_max_pct": 98,
      "umidade_min_pct": 67,
      "vento_max_kmh": 3.8,
      "rajada_max_kmh": 20.5,
      "radiacao_mj_m2": 16.7,
      "evapotranspiracao_mm": 3.48
    },
    {
      "data": "2026-04-15",
      "chuva_mm": 14.0,
      "prob_chuva_pct": 53,
      "temp_max_c": 30.0,
      "temp_min_c": 24.3,
      "umidade_max_pct": 97,
      "umidade_min_pct": 75,
      "vento_max_kmh": 5.6,
      "rajada_max_kmh": 21.2,
      "radiacao_mj_m2": 14.4,
      "evapotranspiracao_mm": 2.99
    },
    {
      "data": "2026-04-16",
      "chuva_mm": 5.4,
      "prob_chuva_pct": 60,
      "temp_max_c": 29.8,
      "temp_min_c": 24.4,
      "umidade_max_pct": 96,
      "umidade_min_pct": 73,
      "vento_max_kmh": 7.2,
      "rajada_max_kmh": 19.4,
      "radiacao_mj_m2": 13.13,
      "evapotranspiracao_mm": 2.7
    },
    {
      "data": "2026-04-17",
      "chuva_mm": 8.5,
      "prob_chuva_pct": 65,
      "temp_max_c": 32.1,
      "temp_min_c": 24.0,
      "umidade_max_pct": 98,
      "umidade_min_pct": 62,
      "vento_max_kmh": 6.4,
      "rajada_max_kmh": 20.5,
      "radiacao_mj_m2": 18.78,
      "evapotranspiracao_mm": 3.95
    },
    {
      "data": "2026-04-18",
      "chuva_mm": 9.1,
      "prob_chuva_pct": 85,
      "temp_max_c": 30.1,
      "temp_min_c": 24.2,
      "umidade_max_pct": 97,
      "umidade_min_pct": 72,
      "vento_max_kmh": 4.4,
      "rajada_max_kmh": 13.7,
      "radiacao_mj_m2": 14.99,
      "evapotranspiracao_mm": 3.1
    },
    {
      "data": "2026-04-19",
      "chuva_mm": 8.9,
      "prob_chuva_pct": 81,
      "temp_max_c": 30.2,
      "temp_min_c": 24.6,
      "umidade_max_pct": 97,
      "umidade_min_pct": 72,
      "vento_max_kmh": 3.1,
      "rajada_max_kmh": 10.4,
      "radiacao_mj_m2": 14.27,
      "evapotranspiracao_mm": 2.97
    },
    {
      "data": "2026-04-20",
      "chuva_mm": 3.2,
      "prob_chuva_pct": 94,
      "temp_max_c": 29.1,
      "temp_min_c": 22.7,
      "umidade_max_pct": 99,
      "umidade_min_pct": 68,
      "vento_max_kmh": 4.2,
      "rajada_max_kmh": 11.5,
      "radiacao_mj_m2": 10.62,
      "evapotranspiracao_mm": 2.17
    },
    {
      "data": "2026-04-21",
      "chuva_mm": 9.0,
      "prob_chuva_pct": 75,
      "temp_max_c": 23.0,
      "temp_min_c": 22.1,
      "umidade_max_pct": 100,
      "umidade_min_pct": 99,
      "vento_max_kmh": 4.1,
      "rajada_max_kmh": 19.8,
      "radiacao_mj_m2": 1.12,
      "evapotranspiracao_mm": 0.37
    },
    {
      "data": "2026-04-22",
      "chuva_mm": 0.0,
      "prob_chuva_pct": 81,
      "temp_max_c": 23.7,
      "temp_min_c": 21.6,
      "umidade_max_pct": 99,
      "umidade_min_pct": 96,
      "vento_max_kmh": 4.2,
      "rajada_max_kmh": 24.1,
      "radiacao_mj_m2": 2.96,
      "evapotranspiracao_mm": 0.69
    },
    {
      "data": "2026-04-23",
      "chuva_mm": 0.0,
      "prob_chuva_pct": 86,
      "temp_max_c": 30.5,
      "temp_min_c": 21.3,
      "umidade_max_pct": 99,
      "umidade_min_pct": 57,
      "vento_max_kmh": 5.7,
      "rajada_max_kmh": 27.4,
      "radiacao_mj_m2": 9.93,
      "evapotranspiracao_mm": 2.11
    },
    {
      "data": "2026-04-24",
      "chuva_mm": 0.9,
      "prob_chuva_pct": 83,
      "temp_max_c": 31.7,
      "temp_min_c": 21.8,
      "umidade_max_pct": 99,
      "umidade_min_pct": 51,
      "vento_max_kmh": 7.2,
      "rajada_max_kmh": 27.4,
      "radiacao_mj_m2": 19.61,
      "evapotranspiracao_mm": 4.1
    },
    {
      "data": "2026-04-25",
      "chuva_mm": 0.6,
      "prob_chuva_pct": 88,
      "temp_max_c": 32.6,
      "temp_min_c": 21.6,
      "umidade_max_pct": 100,
      "umidade_min_pct": 52,
      "vento_max_kmh": 6.6,
      "rajada_max_kmh": 20.2,
      "radiacao_mj_m2": 19.31,
      "evapotranspiracao_mm": 3.94
    },
    {
      "data": "2026-04-26",
      "chuva_mm": 1.5,
      "prob_chuva_pct": 84,
      "temp_max_c": 32.9,
      "temp_min_c": 22.0,
      "umidade_max_pct": 100,
      "umidade_min_pct": 51,
      "vento_max_kmh": 7.2,
      "rajada_max_kmh": 10.8,
      "radiacao_mj_m2": 21.45,
      "evapotranspiracao_mm": 4.44
    },
    {
      "data": "2026-04-27",
      "chuva_mm": 1.2,
      "prob_chuva_pct": 85,
      "temp_max_c": 33.2,
      "temp_min_c": 22.0,
      "umidade_max_pct": 100,
      "umidade_min_pct": 50,
      "vento_max_kmh": 5.4,
      "rajada_max_kmh": 7.6,
      "radiacao_mj_m2": 19.16,
      "evapotranspiracao_mm": 3.9
    },
    {
      "data": "2026-04-28",
      "chuva_mm": 2.2,
      "prob_chuva_pct": 88,
      "temp_max_c": 32.0,
      "temp_min_c": 22.2,
      "umidade_max_pct": 99,
      "umidade_min_pct": 55,
      "vento_max_kmh": 4.2,
      "rajada_max_kmh": null,
      "radiacao_mj_m2": 14.64,
      "evapotranspiracao_mm": 3.02
    }
  ]
}